LICENSE
MANIFEST.in
README.md
setup.cfg
setup.py
tap_stripe/__init__.py
tap_stripe/schemas/balance_transactions.json
tap_stripe/schemas/charges.json
tap_stripe/schemas/coupons.json
tap_stripe/schemas/customers.json
tap_stripe/schemas/events.json
tap_stripe/schemas/invoice_items.json
tap_stripe/schemas/invoice_line_items.json
tap_stripe/schemas/invoices.json
tap_stripe/schemas/payouts.json
tap_stripe/schemas/plans.json
tap_stripe/schemas/subscription_items.json
tap_stripe/schemas/subscriptions.json
tap_stripe/schemas/transfers.json
tap_stripe/schemas/shared/discount.json
tap_stripe/schemas/shared/plan.json
tap_stripe/schemas/shared/source.json
tap_stripe2.egg-info/PKG-INFO
tap_stripe2.egg-info/SOURCES.txt
tap_stripe2.egg-info/dependency_links.txt
tap_stripe2.egg-info/entry_points.txt
tap_stripe2.egg-info/requires.txt
tap_stripe2.egg-info/top_level.txt